{
  "title": "PolicyDefinitionOperations_ListByEvaluationEngine_MaximumSet_Gen - generated by [MaximumSet] rule",
  "operationId": "PolicyDefinitionOperations_ListByEvaluationEngine",
  "parameters": {
    "api-version": "2024-06-01-preview",
    "subscriptionId": "F1B8415A-6FB1-4F15-954C-E3DA7ACF0584",
    "resourceGroupName": "rgopenapi",
    "evaluationEngineName": "ysqpnlijg"
  },
  "responses": {
    "200": {
      "body": {
        "value": [
          {
            "properties": {},
            "id": "zkipzfjkej",
            "name": "uyfbqhfaiwjwbzrvbfekahjarlie",
            "type": "joexyqshabusdyc",
            "systemData": {
              "createdBy": "xe",
              "createdByType": "User",
              "createdAt": "2024-05-31T22:20:20.366Z",
              "lastModifiedBy": "itbuni",
              "lastModifiedByType": "User",
              "lastModifiedAt": "2024-05-31T22:20:20.366Z"
            }
          }
        ],
        "nextLink": "https://microsoft.com/a"
      }
    }
  }
}
