{
  "title": "KnowledgeBases_CreateOrReplaceKnowledgeBase_MinimumSet",
  "operationId": "KnowledgeBases_CreateOrReplaceKnowledgeBase",
  "parameters": {
    "api-version": "2024-11-01-preview",
    "catalogName": "nwtaybsfcnibrfg",
    "knowledgeBaseName": "yy",
    "resource": {
      "vertical": "Chemistry",
      "attributes": {
        "createdByType": "User",
        "lastModifiedBy": "bzwtgzxidfljvkuwdrgwduqpskyao",
        "lastModifiedByType": "User"
      },
      "definitionContent": "huqwkqqjqzretbe"
    }
  },
  "responses": {
    "200": {
      "body": {
        "name": "qofzpwvfistwenqcarfxuq",
        "id": "wwthywbwuvwuqfurwuhpmb",
        "author": "btojpltgmcdyigtthkhrasf",
        "vertical": "Chemistry",
        "attributes": {
          "createdAt": "2025-02-21T20:00:15.700Z",
          "createdBy": "ceu",
          "createdByType": "User",
          "lastModifiedAt": "2025-02-21T20:00:15.700Z",
          "lastModifiedBy": "bzwtgzxidfljvkuwdrgwduqpskyao",
          "lastModifiedByType": "User",
          "description": "zditoxjajfppymtnsihaf",
          "category": "sqkfqmpjxp",
          "license": "qxrzfg",
          "copilotInstruction": "jyzsmcxhvreqdr",
          "infraType": "wjpxfzjprftmvigslzqym",
          "version": "npbuxbtfswzpfpta"
        }
      }
    },
    "201": {
      "body": {
        "name": "qofzpwvfistwenqcarfxuq",
        "id": "wwthywbwuvwuqfurwuhpmb",
        "author": "btojpltgmcdyigtthkhrasf",
        "vertical": "Chemistry",
        "attributes": {
          "createdAt": "2025-02-21T20:00:15.700Z",
          "createdBy": "ceu",
          "createdByType": "User",
          "lastModifiedAt": "2025-02-21T20:00:15.700Z",
          "lastModifiedBy": "bzwtgzxidfljvkuwdrgwduqpskyao",
          "lastModifiedByType": "User",
          "description": "zditoxjajfppymtnsihaf",
          "category": "sqkfqmpjxp",
          "license": "qxrzfg",
          "copilotInstruction": "jyzsmcxhvreqdr",
          "infraType": "wjpxfzjprftmvigslzqym",
          "version": "npbuxbtfswzpfpta"
        }
      }
    }
  }
}
