{
  "title": "Operations_List",
  "operationId": "Operations_List",
  "parameters": {
    "api-version": "2024-12-01"
  },
  "responses": {
    "200": {
      "body": {
        "value": [
          {
            "name": "mzwjifcbmcpkvfyqlbgkwbxla",
            "isDataAction": true,
            "display": {
              "provider": "nluemmyzeaarujbxzwdyes",
              "resource": "bandwaycwejesgeovbslxqiclbm",
              "operation": "hjv",
              "description": "wbsvibgvqqdfbeiwjai"
            },
            "origin": "user",
            "actionType": "Internal"
          }
        ],
        "nextLink": "https://microsoft.com/a"
      }
    }
  }
}