{
  "title": "DataContainers_Update_MaximumSet - generated by [MaximumSet] rule",
  "operationId": "DataContainers_Update",
  "parameters": {
    "api-version": "2025-07-01-preview",
    "subscriptionId": "7E37EAB0-7576-4EDC-8AE1-EBD9B8BDC7D1",
    "resourceGroupName": "rgdiscovery",
    "dataContainerName": "85e9b6acb2f029731e",
    "properties": {
      "properties": {
        "credentials": [
          {
            "name": "wfer",
            "kind": "Credential",
            "description": "xobfoa"
          }
        ]
      },
      "tags": {}
    }
  },
  "responses": {
    "200": {
      "body": {
        "id": "/subscriptions/7E37EAB0-7576-4EDC-8AE1-EBD9B8BDC7D1/resourceGroups/rgdiscovery/providers/Private.Discovery/dataContainers/85e9b6acb2f029731e",
        "name": "85e9b6acb2f029731e",
        "tags": {},
        "location": "s",
        "type": "bxaoochyoiocaerlji",
        "systemData": {
          "createdBy": "yrrhqinihbrmwffwjxsupoikfuei",
          "createdByType": "User",
          "createdAt": "2025-05-08T13:23:13.958Z",
          "lastModifiedBy": "sfsnftzqhiidrxzafqrsmvbezukd",
          "lastModifiedByType": "User",
          "lastModifiedAt": "2025-05-08T13:23:13.958Z"
        },
        "properties": {
          "dataStore": {
            "kind": "DataStore"
          },
          "credentials": [
            {
              "name": "wfer",
              "kind": "Credential",
              "description": "xobfoa"
            }
          ],
          "provisioningState": "Succeeded"
        }
      }
    },
    "202": {
      "headers": {
        "location": "https://contoso.com/operationstatus"
      }
    }
  }
}
