{
  "title": "DataAssets_Update_MaximumSet - generated by [MaximumSet] rule",
  "operationId": "DataAssets_Update",
  "parameters": {
    "api-version": "2025-07-01-preview",
    "subscriptionId": "6424B224-1EB0-496A-A3AB-000914D362D1",
    "resourceGroupName": "rgdiscovery",
    "dataContainerName": "6d5f64f35488f138eb",
    "dataAssetName": "0147077e0d562f48ea",
    "properties": {
      "properties": {
        "description": "pk"
      },
      "tags": {
        "key3993": "nwunc"
      }
    }
  },
  "responses": {
    "200": {
      "body": {
        "id": "/subscriptions/6424B224-1EB0-496A-A3AB-000914D362D1/resourceGroups/rgdiscovery/providers/Private.Discovery/dataContainers/6d5f64f35488f138eb/dataAssets/0147077e0d562f48ea",
        "name": "0147077e0d562f48ea",
        "tags": {
          "key6145": "cz"
        },
        "location": "uesxd",
        "type": "bjidrxg",
        "systemData": {
          "createdBy": "aosodaezvbek",
          "createdByType": "User",
          "createdAt": "2025-04-15T15:26:25.917Z",
          "lastModifiedBy": "mfwsdhbgpnqyuhzsjgzdgw",
          "lastModifiedByType": "User",
          "lastModifiedAt": "2025-04-15T15:26:25.917Z"
        },
        "properties": {
          "description": "edegxgpjltzu",
          "provisioningState": "Succeeded",
          "path": "pq"
        }
      }
    },
    "202": {
      "headers": {
        "location": "https://contoso.com/operationstatus"
      }
    }
  }
}
