{
  "title": "DataAssets_CreateOrUpdate_MaximumSet - generated by [MaximumSet] rule",
  "operationId": "DataAssets_CreateOrUpdate",
  "parameters": {
    "api-version": "2025-07-01-preview",
    "subscriptionId": "7E37EAB0-7576-4EDC-8AE1-EBD9B8BDC7D1",
    "resourceGroupName": "rgdiscovery",
    "dataContainerName": "1e6bdb8514fbb7d3d3",
    "dataAssetName": "0c12f55d200c8b8f09",
    "resource": {
      "properties": {
        "description": "dpcmgkfjaft"
      },
      "tags": {
        "key7344": "spptsujfdpca"
      },
      "location": "rmwwyfx"
    }
  },
  "responses": {
    "200": {
      "body": {
        "id": "/subscriptions/7E37EAB0-7576-4EDC-8AE1-EBD9B8BDC7D1/resourceGroups/rgdiscovery/providers/Private.Discovery/dataContainers/1e6bdb8514fbb7d3d3/dataAssets/0c12f55d200c8b8f09",
        "name": "0c12f55d200c8b8f09",
        "tags": {
          "key7344": "spptsujfdpca"
        },
        "location": "rmwwyfx",
        "type": "wxbxqo",
        "systemData": {
          "createdBy": "yrrhqinihbrmwffwjxsupoikfuei",
          "createdByType": "User",
          "createdAt": "2025-05-08T13:23:13.958Z",
          "lastModifiedBy": "sfsnftzqhiidrxzafqrsmvbezukd",
          "lastModifiedByType": "User",
          "lastModifiedAt": "2025-05-08T13:23:13.958Z"
        },
        "properties": {
          "description": "dpcmgkfjaft",
          "provisioningState": "Succeeded",
          "path": "bszvhzkxcacddekkd"
        }
      }
    },
    "201": {
      "headers": {
        "Azure-AsyncOperation": "https://contoso.com/operationstatus"
      },
      "body": {
        "id": "/subscriptions/7E37EAB0-7576-4EDC-8AE1-EBD9B8BDC7D1/resourceGroups/rgdiscovery/providers/Private.Discovery/dataContainers/1e6bdb8514fbb7d3d3/dataAssets/0c12f55d200c8b8f09",
        "name": "0c12f55d200c8b8f09",
        "tags": {
          "key7344": "spptsujfdpca"
        },
        "location": "rmwwyfx",
        "type": "wxbxqo",
        "systemData": {
          "createdBy": "yrrhqinihbrmwffwjxsupoikfuei",
          "createdByType": "User",
          "createdAt": "2025-05-08T13:23:13.958Z",
          "lastModifiedBy": "sfsnftzqhiidrxzafqrsmvbezukd",
          "lastModifiedByType": "User",
          "lastModifiedAt": "2025-05-08T13:23:13.958Z"
        },
        "properties": {
          "description": "dpcmgkfjaft",
          "provisioningState": "Succeeded",
          "path": "bszvhzkxcacddekkd"
        }
      }
    }
  }
}
