{
  "title": "ProvisionedClusterUpgradeProfiles_GetUpgradeProfile",
  "operationId": "ProvisionedClusterUpgradeProfiles_GetUpgradeProfile",
  "parameters": {
    "api-version": "2024-06-01-preview",
    "connectedClusterResourceUri": "yssytqdziuduqkhedmzmyykydda"
  },
  "responses": {
    "200": {
      "body": {
        "properties": {
          "provisioningState": "Succeeded",
          "controlPlaneProfile": {
            "kubernetesVersion": "ryoeml",
            "osType": "Windows",
            "upgrades": [
              {
                "kubernetesVersion": "s",
                "isPreview": true
              }
            ]
          }
        },
        "id": "vzupkkzizkdf",
        "name": "wlfqvjrkz",
        "type": "wsimquprlxstecakrng",
        "systemData": {
          "createdBy": "urzeooikfllpguxjhqqgtu",
          "createdByType": "User",
          "createdAt": "2024-06-18T19:47:30.251Z",
          "lastModifiedBy": "mjkfnqvuvkbdjqxvyitovyy",
          "lastModifiedByType": "User",
          "lastModifiedAt": "2024-06-18T19:47:30.251Z"
        }
      }
    }
  }
}
