{
  "title": "DataContainers_Get_MaximumSet - generated by [MaximumSet] rule",
  "operationId": "DataContainers_Get",
  "parameters": {
    "api-version": "2025-07-01-preview",
    "subscriptionId": "A549F3B8-06A4-4552-9B73-795D1E7C331D",
    "resourceGroupName": "rgdiscovery",
    "dataContainerName": "cf42be7ac85d7708a0"
  },
  "responses": {
    "200": {
      "body": {
        "id": "/subscriptions/31735C59-6307-4464-8B80-3675223F23D2/resourceGroups/rgdiscovery/providers/Microsoft.Discovery/DataContainers/cf42be7ac85d7708a0",
        "name": "cf42be7ac85d7708a0",
        "tags": {
          "key2357": "acfevh"
        },
        "location": "ncuxd",
        "type": "ewdiaxjuqudbmhgjpsybver",
        "systemData": {
          "createdBy": "slpallbyqblzezfnxrrhsdljgjql",
          "createdByType": "User",
          "createdAt": "2025-05-23T13:22:17.453Z",
          "lastModifiedBy": "dhrksfrfilfbuddnkpumgk",
          "lastModifiedByType": "User",
          "lastModifiedAt": "2025-05-23T13:22:17.453Z"
        },
        "properties": {
          "provisioningState": "Succeeded",
          "dataStore": {
            "kind": "DataStore"
          },
          "credentials": [
            {
              "name": "koqpofqojngybhelv",
              "kind": "Credential",
              "description": "qerwidcrrohtesjmxqxlrzg"
            }
          ]
        }
      }
    }
  }
}
