{
  "title": "Projects_Get_MaximumSet - generated by [MaximumSet] rule",
  "operationId": "Projects_Get",
  "parameters": {
    "api-version": "2025-07-01-preview",
    "subscriptionId": "7E37EAB0-7576-4EDC-8AE1-EBD9B8BDC7D1",
    "resourceGroupName": "rgdiscovery",
    "workspaceName": "c6b1ef356a099e7857",
    "projectName": "516ab6274df4972022"
  },
  "responses": {
    "200": {
      "body": {
        "id": "/subscriptions/7E37EAB0-7576-4EDC-8AE1-EBD9B8BDC7D1/resourceGroups/rgdiscovery/providers/Private.Discovery/workspaces/c6b1ef356a099e7857/projects/516ab6274df4972022",
        "name": "516ab6274df4972022",
        "tags": {},
        "location": "ivjicwklanewxwnyzueleqk",
        "type": "lnqexupvnvppnhnaobnstbsevut",
        "systemData": {
          "createdBy": "yrrhqinihbrmwffwjxsupoikfuei",
          "createdByType": "User",
          "createdAt": "2025-05-08T13:23:13.958Z",
          "lastModifiedBy": "sfsnftzqhiidrxzafqrsmvbezukd",
          "lastModifiedByType": "User",
          "lastModifiedAt": "2025-05-08T13:23:13.958Z"
        },
        "properties": {
          "agentIds": [
            "/subscriptions/31735C59-6307-4464-8B80-3675223F23D2/providers/Microsoft.Discovery/agents/agent12"
          ],
          "knowledgeBaseIds": [
            "kxcgigtuboeuczmo"
          ],
          "dataContainerIds": [
            "/subscriptions/31735C59-6307-4464-8B80-3675223F23D2/providers/Microsoft.Discovery/dataContainers/dataContainer12"
          ],
          "provisioningState": "Succeeded"
        }
      }
    }
  }
}
