{
  "title": "Workflows_CreateOrUpdate_MaximumSet - generated by [MaximumSet] rule",
  "operationId": "Workflows_CreateOrUpdate",
  "parameters": {
    "api-version": "2025-07-01-preview",
    "subscriptionId": "6EDCA832-5C88-4584-9DAC-D1B3416F3E29",
    "resourceGroupName": "rgdiscovery",
    "workflowName": "10e691f1c8bbb0705c",
    "resource": {
      "properties": {
        "version": "grdmgu",
        "definitionContent": {}
      },
      "tags": {
        "key2793": "fhfcfktdfsyvqjfvwum"
      },
      "location": "showwsgwvws"
    }
  },
  "responses": {
    "200": {
      "body": {
        "id": "/subscriptions/31735C59-6307-4464-8B80-3675223F23D2/resourceGroups/rgdiscovery/providers/Microsoft.Discovery/Workflows/10e691f1c8bbb0705c",
        "name": "10e691f1c8bbb0705c",
        "tags": {
          "key2793": "fhfcfktdfsyvqjfvwum"
        },
        "location": "showwsgwvws",
        "type": "hwebyeaquzifdpumfrvitmyevyxki",
        "systemData": {
          "createdBy": "ahqqvlsgx",
          "createdByType": "User",
          "createdAt": "2025-05-23T00:31:48.957Z",
          "lastModifiedBy": "qwueqsgufqajnahfxkautmqbaezt",
          "lastModifiedByType": "User",
          "lastModifiedAt": "2025-05-23T00:31:48.957Z"
        },
        "properties": {
          "provisioningState": "Succeeded",
          "version": "grdmgu",
          "definitionContent": {}
        }
      }
    },
    "201": {
      "headers": {
        "Azure-AsyncOperation": "https://contoso.com/operationstatus"
      },
      "body": {
        "id": "/subscriptions/31735C59-6307-4464-8B80-3675223F23D2/resourceGroups/rgdiscovery/providers/Microsoft.Discovery/Workflows/10e691f1c8bbb0705c",
        "name": "10e691f1c8bbb0705c",
        "tags": {
          "key2793": "fhfcfktdfsyvqjfvwum"
        },
        "location": "showwsgwvws",
        "type": "hwebyeaquzifdpumfrvitmyevyxki",
        "systemData": {
          "createdBy": "ahqqvlsgx",
          "createdByType": "User",
          "createdAt": "2025-05-23T00:31:48.957Z",
          "lastModifiedBy": "qwueqsgufqajnahfxkautmqbaezt",
          "lastModifiedByType": "User",
          "lastModifiedAt": "2025-05-23T00:31:48.957Z"
        },
        "properties": {
          "provisioningState": "Succeeded",
          "version": "grdmgu",
          "definitionContent": {}
        }
      }
    }
  }
}
