{
  "title": "Operations_List_MaximumSet - generated by [MaximumSet] rule",
  "operationId": "Operations_List",
  "parameters": {
    "api-version": "2025-05-01-preview"
  },
  "responses": {
    "200": {
      "body": {
        "value": [
          {
            "name": "Microsoft.HealthcareInterop/operations/read",
            "isDataAction": true,
            "display": {
              "provider": "Microsoft HealthcareInterop",
              "resource": "Operations",
              "operation": "Read Operations",
              "description": "byppvrlrmamxmggvq"
            },
            "origin": "user",
            "actionType": "Internal"
          }
        ],
        "nextLink": "https://microsoft.com/a"
      }
    }
  }
}
