{
  "parameters": {
    "subscriptionId": "mySubscriptionId",
    "api-version": "2021-08-10-privatepreview"
  },
  "responses": {
    "200": {
      "body": {
        "value": [
          {
            "id": "/subscriptions/mySubscriptionId/resourceGroups/prodResourceGroup/providers/Microsoft.AzureCis/dstsServiceAccounts/prodUSEastAzcis",
            "name": "prodUSEastAzcis",
            "type": "Microsoft.AzureCis/dstsServiceAccounts",
            "location": "eastus",
            "provisioningState": "Succeeded",
            "properties": {
              "AccountName": "prod-useast.azcis.trafficmanager.net",
              "GroupName": "ProductionGroup"
            }
          },
          {
            "id": "/subscriptions/mySubscriptionId/resourceGroups/canaryResourceGroup/providers/Microsoft.AzureCis/dstsServiceAccounts/canaryUSEastAzcis",
            "name": "canaryUSEastAzcis",
            "type": "Microsoft.AzureCis/dstsServiceAccounts",
            "location": "eastus",
            "provisioningState": "Succeeded",
            "properties": {
              "AccountName": "canary-useast.azcis.trafficmanager.net",
              "GroupName": "CanaryGroup"
            }
          },
          {
            "id": "/subscriptions/mySubscriptionId/resourceGroups/prodResourceGroup/providers/Microsoft.AzureCis/dstsServiceAccounts/prodUSWestAzcis",
            "name": "prodUSWestAzcis",
            "type": "Microsoft.AzureCis/dstsServiceAccounts",
            "location": "westus",
            "provisioningState": "Succeeded",
            "properties": {
              "AccountName": "prod-uswest.azcis.trafficmanager.net",
              "GroupName": "ProductionGroup"
            }
          },
          {
            "id": "/subscriptions/mySubscriptionId/resourceGroups/canaryResourceGroup/providers/Microsoft.AzureCis/dstsServiceAccounts/canaryUSWestAzcis",
            "name": "canaryUSWestAzcis",
            "type": "Microsoft.AzureCis/dstsServiceAccounts",
            "location": "westus",
            "provisioningState": "Succeeded",
            "properties": {
              "AccountName": "canary-uswest.azcis.trafficmanager.net",
              "GroupName": "CanaryGroup"
            }
          }
        ]
      }
    }
  }
}
