{
  "parameters": {
    "api-version": "2024-10-01-preview"
  },
  "responses": {
    "200": {
      "body": {
        "value": [
          {
            "name": "Private.ArcContainerStorage/acstorconfigurations/read",
            "display": {
              "provider": "Private.ArcContainerStorage",
              "resource": "ACStorConfiguration",
              "operation": "Read ACStorConfiguration",
              "description": "Read operation for ACStorConfiguration resource."
            }
          },
          {
            "name": "Private.ArcContainerStorage/acstorconfigurations/write",
            "display": {
              "provider": "Private.ArcContainerStorage",
              "resource": "ACStorConfiguration",
              "operation": "Write ACStorConfiguration",
              "description": "Write operation for ACStorConfiguration resource."
            }
          }
        ]
      }
    }
  }
}
