{
  "title": "KnowledgeBaseDefinitions_GetKnowledgeBaseDefinition_MaximumSet - generated by [MaximumSet] rule",
  "operationId": "KnowledgeBaseDefinitions_GetKnowledgeBaseDefinition",
  "parameters": {
    "api-version": "2025-07-01-preview",
    "catalogName": "70e3af623e258bbcf7",
    "knowledgeBaseName": "c8137bee9edd5171bb"
  },
  "responses": {
    "200": {
      "body": {
        "id": "/catalogs/70e3af623e258bbcf7/knowledgeBaseDefinitions/c8137bee9edd5171bb",
        "name": "c8137bee9edd5171bb",
        "definitionContent": "artifact_definition_content_in_yaml_format",
        "createdAt": "2025-04-11T14:37:32.397Z",
        "createdBy": "xixbaiasiqpwtyheugppif",
        "createdByType": "User",
        "lastModifiedAt": "2025-04-11T14:37:32.397Z",
        "lastModifiedBy": "zrgkjrahlsdltnnuufxpdzjoucrbr",
        "lastModifiedByType": "User",
        "catalogName": "Replace this value with a string matching RegExp ^[a-zA-Z0-9-]{3,24}$",
        "description": "xwjdsabateeejndr",
        "scope": "Archived",
        "author": "flglyqxymvkpjv",
        "tags": [
          {
            "key": "egad",
            "value": "wvwmgyshzsd"
          }
        ],
        "category": "iq",
        "license": "ypjmpdkvxhphcbkh",
        "copilotInstruction": "vnjzmgswvhbqisvqodnih",
        "infraType": "lyrwn",
        "version": "wwvlimdf"
      }
    }
  }
}
