{
  "title": "KnowledgeBaseDefinitions_CreateOrUpdateKnowledgeBaseDefinition_MaximumSet - generated by [MaximumSet] rule",
  "operationId": "KnowledgeBaseDefinitions_CreateOrUpdateKnowledgeBaseDefinition",
  "parameters": {
    "api-version": "2025-07-01-preview",
    "catalogName": "a992529d3533a64cde",
    "knowledgeBaseName": "4bd857243fe05236d8",
    "resource": {
      "definitionContent": "artifact_definition_content_in_yaml_format",
      "scope": "Archived",
      "tags": [
        {
          "key": "ejusepuwgocjjfmrktbo",
          "value": "czrzkrwwjxoayiqzm"
        }
      ]
    }
  },
  "responses": {
    "200": {
      "body": {
        "id": "/catalogs/a992529d3533a64cde/knowledgeBaseDefinitions/4bd857243fe05236d8",
        "name": "4bd857243fe05236d8",
        "definitionContent": "artifact_definition_content_in_yaml_format",
        "version": "mtvhfpdpbsitsexbxpuutlfmxnljj",
        "catalogName": "Replace this value with a string matching RegExp ^[a-zA-Z0-9-]{3,24}$",
        "createdAt": "2025-04-16T17:58:31.310Z",
        "createdBy": "ahaznytqdviwk",
        "createdByType": "User",
        "lastModifiedAt": "2025-04-16T17:58:31.310Z",
        "lastModifiedBy": "gxedfcjacuuqputgsrwkolilxmtgbw",
        "lastModifiedByType": "User",
        "description": "fisasw",
        "scope": "Archived",
        "author": "kaxqrykjytcenfris",
        "tags": [
          {
            "key": "ejusepuwgocjjfmrktbo",
            "value": "czrzkrwwjxoayiqzm"
          }
        ],
        "category": "axqrkyyiqnodxcl",
        "license": "wmueozbygiwd",
        "copilotInstruction": "yzzfaahxpidcbhthnqzmlaohmvwak",
        "infraType": "vxfmjbhjhfytfrajutlyb"
      }
    },
    "201": {
      "body": {
        "id": "/catalogs/a992529d3533a64cde/knowledgeBaseDefinitions/4bd857243fe05236d8",
        "name": "4bd857243fe05236d8",
        "definitionContent": "artifact_definition_content_in_yaml_format",
        "version": "mtvhfpdpbsitsexbxpuutlfmxnljj",
        "catalogName": "Replace this value with a string matching RegExp ^[a-zA-Z0-9-]{3,24}$",
        "createdAt": "2025-04-16T17:58:31.310Z",
        "createdBy": "ahaznytqdviwk",
        "createdByType": "User",
        "lastModifiedAt": "2025-04-16T17:58:31.310Z",
        "lastModifiedBy": "gxedfcjacuuqputgsrwkolilxmtgbw",
        "lastModifiedByType": "User",
        "description": "fisasw",
        "scope": "Archived",
        "author": "kaxqrykjytcenfris",
        "tags": [
          {
            "key": "ejusepuwgocjjfmrktbo",
            "value": "czrzkrwwjxoayiqzm"
          }
        ],
        "category": "axqrkyyiqnodxcl",
        "license": "wmueozbygiwd",
        "copilotInstruction": "yzzfaahxpidcbhthnqzmlaohmvwak",
        "infraType": "vxfmjbhjhfytfrajutlyb"
      }
    }
  }
}
