{
  "title": "EvaluationEnginePolicyDefinitionOperations_Update",
  "operationId": "EvaluationEnginePolicyDefinitionOperations_Update",
  "parameters": {
    "api-version": "2024-06-01-preview",
    "subscriptionId": "3DE23944-97B7-43D9-AA65-1C397105D250",
    "resourceGroupName": "rgopenapi",
    "evaluationEngineName": "Replace this value with a string matching RegExp ^[a-zA-Z0-9-]{3,24}$",
    "policyName": "Replace this value with a string matching RegExp ^[a-zA-Z0-9-]{3,24}$",
    "properties": {
      "properties": {
        "version": "imnmsikdgwcjgvit",
        "description": "Replace this value with a string matching RegExp ^[a-zA-Z0-9 ]{3,250}$",
        "parameters": {},
        "metadata": {},
        "applicabilityConditions": "povsfximsmtesqvrjcgavcdomycvq",
        "complianceConditions": "jbtzbszuuckjobbhqwadciskwrug",
        "effect": {}
      }
    }
  },
  "responses": {
    "200": {
      "body": {
        "properties": {
          "provisioningState": "Succeeded",
          "version": "ahzcnofhbd",
          "description": "Replace this value with a string matching RegExp ^[a-zA-Z0-9 ]{3,250}$",
          "parameters": {},
          "metadata": {},
          "applicabilityConditions": "vzxocm",
          "complianceConditions": "jgecwtpadbntsjtqrcxkf",
          "effect": {}
        },
        "id": "cxwygfbonezcdpzzdsqaamaya",
        "name": "lmfqljhmpflqvbwxe",
        "type": "mjlvfmxtjlj",
        "systemData": {
          "createdBy": "fth",
          "createdByType": "User",
          "createdAt": "2024-07-31T20:35:19.561Z",
          "lastModifiedBy": "swarbtx",
          "lastModifiedByType": "User",
          "lastModifiedAt": "2024-07-31T20:35:19.562Z"
        }
      }
    }
  }
}