{
  "title": "EvaluationEnginePolicyAssignmentOperations_Get",
  "operationId": "EvaluationEnginePolicyAssignmentOperations_Get",
  "parameters": {
    "api-version": "2024-06-01-preview",
    "subscriptionId": "FAE41A55-EE00-4693-BC4D-74F2FA1C076E",
    "resourceGroupName": "rgopenapi",
    "evaluationEngineName": "Replace this value with a string matching RegExp ^[a-zA-Z0-9-]{3,24}$",
    "policyAssignmentName": "Replace this value with a string matching RegExp ^[a-zA-Z0-9-]{3,24}$"
  },
  "responses": {
    "200": {
      "body": {
        "properties": {
          "provisioningState": "Succeeded",
          "version": "ctyrgyqe",
          "scopes": [
            "rttyjbjccjdf"
          ],
          "notScopes": [
            "ztvjwwnzxnfjfoqpa"
          ],
          "description": "Replace this value with a string matching RegExp ^[a-zA-Z0-9 ]{3,250}$",
          "metadata": {},
          "policyDefinitionId": "kbkadcehzuccwmzgvd",
          "parameters": "wgtsk"
        },
        "id": "mbygtqga",
        "name": "jtwbootozoippozolwyqotbzdgdwbb",
        "type": "jmduklnyfyphi",
        "systemData": {
          "createdBy": "ajgxrnsxqg",
          "createdByType": "User",
          "createdAt": "2024-08-02T21:28:26.121Z",
          "lastModifiedBy": "mggvstsstqkmbpc",
          "lastModifiedByType": "User",
          "lastModifiedAt": "2024-08-02T21:28:26.122Z"
        }
      }
    }
  }
}