{
  "title": "EvaluationEngineOperations_Update_MaximumSet_Gen - generated by [MaximumSet] rule",
  "operationId": "EvaluationEngineOperations_Update",
  "parameters": {
    "api-version": "2024-06-01-preview",
    "subscriptionId": "88165D75-ACF1-46C7-BF83-09F968052E39",
    "resourceGroupName": "rgopenapi",
    "evaluationEngineName": "Replace this value with a string matching RegExp ^[a-zA-Z0-9-]{3,24}$",
    "properties": {
      "tags": {
        "key1691": "ka"
      }
    }
  },
  "responses": {
    "200": {
      "body": {
        "properties": {
          "provisioningState": "Succeeded"
        },
        "tags": {
          "key4437": "lkyvbnfmcbpnqsamjptxq"
        },
        "location": "utwyjrbxsekx",
        "id": "aijytz",
        "name": "xk",
        "type": "ywgepakvokqnlkzuvruqewdrquyxtx",
        "systemData": {
          "createdBy": "vcogshmvlsafjfkglvlg",
          "createdByType": "User",
          "createdAt": "2024-06-18T06:17:18.885Z",
          "lastModifiedBy": "jtgwofnoyfnpdytocnl",
          "lastModifiedByType": "User",
          "lastModifiedAt": "2024-06-18T06:17:18.885Z"
        }
      }
    },
    "202": {
      "headers": {
        "location": "https://contoso.com/operationstatus"
      }
    }
  }
}