{
  "title": "DataContainers_Get_MaximumSet - generated by [MaximumSet] rule",
  "operationId": "DataContainers_Get",
  "parameters": {
    "api-version": "2024-11-01-preview",
    "subscriptionId": "EF89D915-CD01-472E-9118-B70648E3CB8C",
    "resourceGroupName": "rgscience",
    "dataContainerName": "de6095492b50002a56"
  },
  "responses": {
    "200": {
      "body": {
        "properties": {
          "provisioningState": "Succeeded",
          "dataStore": {
            "kind": "DataStore"
          },
          "credentials": [
            {
              "name": "spbmdgrojjstfrwwcukijvhuje",
              "kind": "Credential",
              "description": "nuivxaabhrhtbwldvhjdkynxxggj"
            }
          ]
        },
        "tags": {
          "key6516": "dit"
        },
        "location": "ohzbttqsbsjorzmqdrllmmztnyyiey",
        "id": "/subscriptions/EF89D915-CD01-472E-9118-B70648E3CB8C/resourceGroups/rgscience/providers/Private.Science/dataContainers/de6095492b50002a56",
        "name": "qfvlgvmhuygezloozergziegiiykf",
        "type": "ngiuqbwosmpadskbcvntvkpv",
        "systemData": {
          "createdBy": "bqjqalezn",
          "createdByType": "User",
          "createdAt": "2025-03-13T18:19:04.565Z",
          "lastModifiedBy": "qngk",
          "lastModifiedByType": "User",
          "lastModifiedAt": "2025-03-13T18:19:04.565Z"
        }
      }
    }
  }
}
