{
  "title": "Workflows_Delete_MaximumSet",
  "operationId": "Workflows_Delete",
  "parameters": {
    "api-version": "2025-01-01-preview",
    "subscriptionId": "B88EC57D-E9AF-4AB4-82DB-373A239E9DBE",
    "resourceGroupName": "rgconfigurationmanager",
    "workflowName": "Replace this value with a string matching RegExp ^[a-z0-9]([-a-z0-9]*[a-z0-9])?(\\.[a-z0-9]([-a-z0-9]*[a-z0-9])?)*$"
  },
  "responses": {
    "202": {
      "headers": {
        "location": "https://contoso.com/operationstatus"
      }
    },
    "204": {}
  }
}