{
  "title": "Investigations_CreateOrReplaceInvestigation_MaximumSet - generated by [MaximumSet] rule",
  "operationId": "Investigations_CreateOrReplaceInvestigation",
  "parameters": {
    "api-version": "2025-07-01-preview",
    "projectName": "cypmdxvwfugaitrm",
    "investigationName": "psssmryrsutbjbx",
    "resource": {
      "status": "Created",
      "description": "yeqonzdpihmjxqndaxpjrijfiueie",
      "tags": [
        {
          "key": "sdkykxiqapteyuydwf",
          "value": "jacjqgrtnqcugawgnmm"
        }
      ],
      "displayName": "mdfphduvidwxekujuutjxbc"
    }
  },
  "responses": {
    "200": {
      "body": {
        "id": "/projects/cypmdxvwfugaitrm/investigations/psssmryrsutbjbx",
        "name": "psssmryrsutbjbx",
        "createdAt": "2025-03-27T20:43:52.942Z",
        "createdBy": "hyo",
        "createdByType": "wt",
        "lastModifiedAt": "2025-03-27T20:43:52.942Z",
        "lastModifiedBy": "curshwvp",
        "lastModifiedByType": "sazopet",
        "status": "Created",
        "description": "yeqonzdpihmjxqndaxpjrijfiueie",
        "tags": [
          {
            "key": "sdkykxiqapteyuydwf",
            "value": "jacjqgrtnqcugawgnmm"
          }
        ],
        "displayName": "mdfphduvidwxekujuutjxbc"
      }
    },
    "201": {
      "body": {
        "id": "/projects/cypmdxvwfugaitrm/investigations/psssmryrsutbjbx",
        "name": "psssmryrsutbjbx",
        "createdAt": "2025-03-27T20:43:52.942Z",
        "createdBy": "hyo",
        "createdByType": "wt",
        "lastModifiedAt": "2025-03-27T20:43:52.942Z",
        "lastModifiedBy": "curshwvp",
        "lastModifiedByType": "sazopet",
        "status": "Created",
        "description": "yeqonzdpihmjxqndaxpjrijfiueie",
        "tags": [
          {
            "key": "sdkykxiqapteyuydwf",
            "value": "jacjqgrtnqcugawgnmm"
          }
        ],
        "displayName": "mdfphduvidwxekujuutjxbc"
      }
    }
  }
}
