{
  "title": "ModelDefinitions_CreateOrUpdateModelDefinition_MinimumSet",
  "operationId": "ModelDefinitions_CreateOrUpdateModelDefinition",
  "parameters": {
    "api-version": "2024-11-01-preview",
    "catalogName": "wkeipmlhtxzohmsqtaoolwomfkpbt",
    "modelName": "oborpkea",
    "resource": {}
  },
  "responses": {
    "200": {
      "body": {
        "vertical": "Chemistry",
        "attributes": {
          "createdByType": "User",
          "lastModifiedBy": "pfqacilwukfx",
          "lastModifiedByType": "User",
          "createdAt": "2025-02-21T18:06:03.937Z",
          "createdBy": "of",
          "lastModifiedAt": "2025-02-21T18:06:03.937Z",
          "description": "nfqmqebynhumynpk",
          "category": "dqznokydh",
          "license": "quxduelsed",
          "version": "eptqbxpyewv",
          "docs": "afkmzvjjtgsqrnabfnidi",
          "repo": "igvrfvedtcbofgrlmstcnm"
        },
        "name": "beuohqqoktpawyknhzr",
        "id": "jvyznvh",
        "author": "lnpjxsavwugsle"
      }
    },
    "201": {
      "body": {
        "vertical": "Chemistry",
        "attributes": {
          "createdByType": "User",
          "lastModifiedBy": "pfqacilwukfx",
          "lastModifiedByType": "User",
          "createdAt": "2025-02-21T18:06:03.937Z",
          "createdBy": "of",
          "lastModifiedAt": "2025-02-21T18:06:03.937Z",
          "description": "nfqmqebynhumynpk",
          "category": "dqznokydh",
          "license": "quxduelsed",
          "version": "eptqbxpyewv",
          "docs": "afkmzvjjtgsqrnabfnidi",
          "repo": "igvrfvedtcbofgrlmstcnm"
        },
        "name": "beuohqqoktpawyknhzr",
        "id": "jvyznvh",
        "author": "lnpjxsavwugsle"
      }
    }
  }
}
