{
  "title": "ToolDefinitions_CreateOrReplaceToolDefinition_MaximumSet",
  "operationId": "ToolDefinitions_CreateOrReplaceToolDefinition",
  "parameters": {
    "api-version": "2024-11-01-preview",
    "catalogName": "o",
    "toolName": "isfagaoips",
    "resource": {
      "tags": [
        {
          "key": "uqtzjaaatpca",
          "value": "ld"
        }
      ],
      "vertical": "Chemistry",
      "attributes": {
        "createdByType": "User",
        "lastModifiedBy": "nlzcdmeywxbuqixnwoeabmi",
        "lastModifiedByType": "User"
      },
      "definitionContent": "sbgcivfdbb"
    }
  },
  "responses": {
    "200": {
      "body": {
        "tags": [
          {
            "key": "uqtzjaaatpca",
            "value": "ld"
          }
        ],
        "vertical": "Chemistry",
        "attributes": {
          "createdByType": "User",
          "lastModifiedBy": "nlzcdmeywxbuqixnwoeabmi",
          "lastModifiedByType": "User",
          "createdAt": "2025-02-21T18:06:04.653Z",
          "createdBy": "mnniublhrbypwbuejup",
          "lastModifiedAt": "2025-02-21T18:06:04.653Z",
          "description": "uapedjahkjozw",
          "category": "ybfchuhwmovjuximnxsnclyajiawsx",
          "license": "uziomhcsllluvpbslnnnevqylxn",
          "version": "amqmqvpryhgsodwjvssofqhdsw",
          "docs": "gbxegdkwgjogmojzktxyv",
          "repo": "zlblvnccqiytmlvzcanhwrlk"
        },
        "name": "wuxhbcqvga",
        "id": "jwt",
        "author": "jiasbyuysbkkmtx"
      }
    },
    "201": {
      "body": {
        "tags": [
          {
            "key": "uqtzjaaatpca",
            "value": "ld"
          }
        ],
        "vertical": "Chemistry",
        "attributes": {
          "createdByType": "User",
          "lastModifiedBy": "nlzcdmeywxbuqixnwoeabmi",
          "lastModifiedByType": "User",
          "createdAt": "2025-02-21T18:06:04.653Z",
          "createdBy": "mnniublhrbypwbuejup",
          "lastModifiedAt": "2025-02-21T18:06:04.653Z",
          "description": "uapedjahkjozw",
          "category": "ybfchuhwmovjuximnxsnclyajiawsx",
          "license": "uziomhcsllluvpbslnnnevqylxn",
          "version": "amqmqvpryhgsodwjvssofqhdsw",
          "docs": "gbxegdkwgjogmojzktxyv",
          "repo": "zlblvnccqiytmlvzcanhwrlk"
        },
        "name": "wuxhbcqvga",
        "id": "jwt",
        "author": "jiasbyuysbkkmtx"
      }
    }
  }
}
