{
  "title": "EdgeStorageConfigurations_List_MaximumSet",
  "operationId": "EdgeStorageConfigurations_List",
  "parameters": {
    "api-version": "2024-10-01-preview",
    "resourceUri": "yggp"
  },
  "responses": {
    "200": {
      "body": {
        "value": [
          {
            "properties": {
              "defaultDiskStorageClasses": [
                "nqwcogaqrrxruzqromzuxfumfqoxmpqbfhlhrkxbqcfbppdqgojkwnaspmqkmantook"
              ],
              "failoverEdgeVolumeConsumers": true,
              "serviceMesh": "osm",
              "workloadIdentity": {
                "clientId": "vdtuubicisylfmpbkkbmvsxyjsuar",
                "tenantId": "vdtuubicisylfmpbkkbmvsxyjsuar"
              },
              "provisioningState": "Succeeded",
              "status": {
                "state": "uakkuwxvnhlpsuhwapewdge",
                "details": "cpanhhqmteaxqfllznkvxelhi"
              }
            },
            "id": "lwgoa",
            "name": "ogneucmbltydkgiepylqmkjjhp",
            "type": "nsstssczbphnyi",
            "systemData": {
              "createdBy": "zdtneahzqg",
              "createdByType": "User",
              "createdAt": "2025-03-11T18:06:18.604Z",
              "lastModifiedBy": "zorravlahdr",
              "lastModifiedByType": "User",
              "lastModifiedAt": "2025-03-11T18:06:18.604Z"
            }
          }
        ],
        "nextLink": "https://microsoft.com/a"
      }
    }
  }
}
